Deluminator/__init__.py
Deluminator/main.py
Deluminator/engine/__init__.py
Deluminator/engine/pd.py
Deluminator/engine/sd.py
Deluminator/engine/source
Deluminator-1.0.0.dist-info/License
Deluminator-1.0.0.dist-info/METADATA
Deluminator-1.0.0.dist-info/WHEEL
Deluminator-1.0.0.dist-info/entry_points.txt
Deluminator-1.0.0.dist-info/top_level.txt
Deluminator-1.0.0.dist-info/RECORD
