Metadata-Version: 2.1
Name: Deluminator
Version: 1.0.0
Summary: This package is a reverse shell generator for Windows systems that uses sockets to establish a connection. It is highly capable of bypassing antivirus software. The package includes a control server and comes with a number of useful features.
Author: Harshdeep Singh
Author-email: ishu.cxx@gmail.com
License: BSD-3-Clause
License-File: License
Requires-Dist: click
Requires-Dist: pyinstaller
Requires-Dist: pyautogui
